sunscreen.py
sunscreen-0.0.4.dist-info/LICENSE
sunscreen-0.0.4.dist-info/METADATA
sunscreen-0.0.4.dist-info/WHEEL
sunscreen-0.0.4.dist-info/entry_points.txt
sunscreen-0.0.4.dist-info/top_level.txt
sunscreen-0.0.4.dist-info/RECORD
